README.md
setup.py
lagan/__init__.py
lagan/error.py
lagan/lagan.py
lagan.egg-info/PKG-INFO
lagan.egg-info/SOURCES.txt
lagan.egg-info/dependency_links.txt
lagan.egg-info/top_level.txt