Metadata-Version: 2.1
Name: lagan
Version: 1.0
Summary: log system
Home-page: https://github.com/jdhxyy/lagan-python
Author: jdh99
Author-email: jdh821@163.com
License: UNKNOWN
Platform: UNKNOWN
